variamos_security/__init__.py
variamos_security/security_config.py
variamos_security/config/__init__.py
variamos_security/config/security_config.py
variamos_security/exceptions/__init__.py
variamos_security/exceptions/variamos_security_exception.py
variamos_security/functions/__init__.py
variamos_security/functions/create_jwt.py
variamos_security/functions/has_permissions.py
variamos_security/functions/has_roles.py
variamos_security/functions/is_authenticated.py
variamos_security/functions/mappers.py
variamos_security/model/__init__.py
variamos_security/model/response_model.py
variamos_security/model/session_info.py
variamos_security/model/session_user.py
variamos_security-0.0.2.dist-info/METADATA
variamos_security-0.0.2.dist-info/WHEEL
variamos_security-0.0.2.dist-info/top_level.txt
variamos_security-0.0.2.dist-info/RECORD
