Metadata-Version: 2.1
Name: variamos-security
Version: 0.0.2
Summary: VariaMos security commons for Python
Home-page: UNKNOWN
Author: VariaMos
Author-email: variamosple@gmail.com
License: UNKNOWN
Platform: UNKNOWN
Classifier: Programming Language :: Python :: 3
Classifier: License :: OSI Approved :: MIT License
Classifier: Operating System :: OS Independent
Requires-Python: >=3.9
Requires-Dist: python-jose
Provides-Extra: fastapi
Requires-Dist: fastapi>=0.115.0; extra == "fastapi"
